diffx/__init__.py
diffx/base.py
diffx/differ.py
diffx/hash.py
diffx/xpath.py
diffx/svg/__init__.py
diffx/svg/coloured_text.py
diffx/svg/coloured_without_text.py
diffx/svg/compact.py
diffx/svg/render_text.py
diffx-1.1.2.dist-info/METADATA
diffx-1.1.2.dist-info/WHEEL
diffx-1.1.2.dist-info/top_level.txt
diffx-1.1.2.dist-info/zip-safe
diffx-1.1.2.dist-info/RECORD
