Metadata-Version: 2.1
Name: diffx
Version: 1.1.2
Summary: compare xml or json files with svg/html report
Home-page: https://github.com/mmoosstt/diffx
Author: mmoosstt
Author-email: diponaut@gmx.de
License: LGPL
Platform: UNKNOWN
Requires-Dist: PySide2
Requires-Dist: lxml
Requires-Dist: svgwrite
Requires-Dist: dicttoxml
